mindsay_sdk/__init__.py
mindsay_sdk/client.py
mindsay_sdk/exc.py
mindsay_sdk/utils.py
mindsay_sdk-1.0.0.dist-info/LICENSE.md
mindsay_sdk-1.0.0.dist-info/METADATA
mindsay_sdk-1.0.0.dist-info/WHEEL
mindsay_sdk-1.0.0.dist-info/top_level.txt
mindsay_sdk-1.0.0.dist-info/RECORD
