Metadata-Version: 2.1
Name: mindsay-sdk
Version: 1.0.0
Summary: Mindsay python client
Home-page: https://github.com/Destygo/mindsay-sdk
Author: Mindsay tech team
Author-email: tech@mindsay.com
License: UNKNOWN
Platform: UNKNOWN
Classifier: Programming Language :: Python :: 3.7
Classifier: Operating System :: OS Independent
Requires-Dist: requests
